hello.cp38-win_amd64.pyd
SELDOMpy/LICENSE.txt
SELDOMpy/README.md
SELDOMpy/__init__.py
SELDOMpy/buildmim.py
SELDOMpy/extras.py
SELDOMpy/gen_exps.py
SELDOMpy/getLBODEmodel.py
SELDOMpy/getRandomLBODEmodel.py
SELDOMpy/optimization.py
SELDOMpy/plot_results.py
SELDOMpy/reduce_fun.py
SELDOMpy/simulate_logic_based_ode.py
SELDOMpy/simulate_logic_based_ode_obs.py
SELDOMpy/examples/MAPK/MAPK.xlsx
SELDOMpy/examples/MAPK/MAPK_training_and_reduce.py
SELDOMpy/examples/MAPK/MAPK_training_and_reduce_pyPESTO.py
SELDOMpy/examples/SP/SP.xlsx
SELDOMpy/examples/SP/SP_training_and_reduce.py
SELDOMpy/examples/SP/SP_training_and_reduce_pyPESTO.py
SELDOMpy/functions/buildmim.py
SELDOMpy/functions/extras.py
SELDOMpy/functions/gen_exps.py
SELDOMpy/functions/getLBODEmodel.py
SELDOMpy/functions/getRandomLBODEmodel.py
SELDOMpy/functions/optimization.py
SELDOMpy/functions/plot_results.py
SELDOMpy/functions/reduce_fun.py
SELDOMpy/functions/simulate_logic_based_ode.py
SELDOMpy/functions/simulate_logic_based_ode_obs.py
SELDOMpy/include/include_amigo/AMIGO_hdf5.h
SELDOMpy/include/include_amigo/AMIGO_model.h
SELDOMpy/include/include_amigo/AMIGO_model_stats.h
SELDOMpy/include/include_amigo/AMIGO_problem.h
SELDOMpy/include/include_amigo/amigoJAC.h
SELDOMpy/include/include_amigo/amigoRHS.h
SELDOMpy/include/include_amigo/amigoSensRHS.h
SELDOMpy/include/include_amigo/simulate_amigo_model.h
SELDOMpy/include/include_cvodes/cvodes/cvodes.h
SELDOMpy/include/include_cvodes/cvodes/cvodes_band.h
SELDOMpy/include/include_cvodes/cvodes/cvodes_bandpre.h
SELDOMpy/include/include_cvodes/cvodes/cvodes_bbdpre.h
SELDOMpy/include/include_cvodes/cvodes/cvodes_dense.h
SELDOMpy/include/include_cvodes/cvodes/cvodes_diag.h
SELDOMpy/include/include_cvodes/cvodes/cvodes_direct.h
SELDOMpy/include/include_cvodes/cvodes/cvodes_lapack.h
SELDOMpy/include/include_cvodes/cvodes/cvodes_spbcgs.h
SELDOMpy/include/include_cvodes/cvodes/cvodes_spgmr.h
SELDOMpy/include/include_cvodes/cvodes/cvodes_spils.h
SELDOMpy-1.0.dist-info/LICENSE.txt
SELDOMpy-1.0.dist-info/METADATA
SELDOMpy-1.0.dist-info/WHEEL
SELDOMpy-1.0.dist-info/top_level.txt
SELDOMpy-1.0.dist-info/RECORD
