Metadata-Version: 2.1
Name: SELDOMpy
Version: 1.0
Summary: Dynamic modelling of cellular signalling networks.
Home-page: https://github.com/lupralo31/SELDOMpy
Download-URL: https://github.com/lupralo31/SELDOMpy/releases/download/0_9_8/SELDOMpy-0.9.8.tar.gz
Author: Luis Prado
Author-email: pradolopezluis@gmail.com
License: GPLv3
Keywords: SELDOMpy,SELDOM,dynamic modelling,cellular signalling networks,biomedical engineering
Classifier: Programming Language :: Python :: 3
Classifier: License :: OSI Approved :: GNU General Public License v3 (GPLv3)
Classifier: Operating System :: OS Independent
License-File: LICENSE.txt
Requires-Dist: numpy
Requires-Dist: scikit-learn
Requires-Dist: pandas
Requires-Dist: mealpy
Requires-Dist: matplotlib
Requires-Dist: setuptools
Requires-Dist: openpyxl
Requires-Dist: pypesto
Requires-Dist: scipy
